{
	"nodes": [
		{
			"domain":"Twitter",
			"selection":"NHdpoq81Ot3",
			"url":"http://www.Twitter.com/2lz7lRY/35MlAq1fkC",
			"visitedCount":"875874",
			"timeAdded":"1341015661",
			"timeDisplay":"2012-06-30 02:21:01"
		},
		{
			"domain":"Youtube",
			"selection":"fDr6tPSy0p4",
			"url":"http://www.Youtube.com/aNgLZid/r2eNUXW4JD",
			"visitedCount":"207615",
			"timeAdded":"1365476196",
			"timeDisplay":"2013-04-09 04:56:36"
		},
		{
			"domain":"Wikipedia",
			"selection":"EGu7xZjvo63",
			"url":"http://www.Wikipedia.com/lC0Ya92/qZ1LVHj5YE",
			"visitedCount":"415750",
			"timeAdded":"1363934047",
			"timeDisplay":"2013-03-22 07:34:07"
		},
		{
			"domain":"Vub",
			"selection":"6gi7G7MqRa3",
			"url":"http://www.Vub.com/M0qG9vX/m8Gzy0gGNh",
			"visitedCount":"478118",
			"timeAdded":"1368254125",
			"timeDisplay":"2013-05-11 08:35:25"
		},
		{
			"domain":"Wikipedia",
			"selection":"YPXb9L1la2E",
			"url":"http://www.Wikipedia.com/KwAzCJN/pfHNj02CUf",
			"visitedCount":"156453",
			"timeAdded":"1341476356",
			"timeDisplay":"2012-07-05 10:19:16"
		},
		{
			"domain":"Vub",
			"selection":"0QnZlHowE1J",
			"url":"http://www.Vub.com/mjN9uxP/6RzhEZpbA2",
			"visitedCount":"197593",
			"timeAdded":"1346646968",
			"timeDisplay":"2012-09-03 06:36:08"
		},
		{
			"domain":"Youtube",
			"selection":"xt8GP79XEDq",
			"url":"http://www.Youtube.com/ARIimg8/XsZVz3NKaT",
			"visitedCount":"695035",
			"timeAdded":"1344648028",
			"timeDisplay":"2012-08-11 03:20:28"
		},
		{
			"domain":"Amazon",
			"selection":"GjiFc5TwZRn",
			"url":"http://www.Amazon.com/YMD6lhs/mZ78wUyXXn",
			"visitedCount":"261856",
			"timeAdded":"1362199647",
			"timeDisplay":"2013-03-02 05:47:27"
		},
		{
			"domain":"Reddit",
			"selection":"mL6YxF4XbYQ",
			"url":"http://www.Reddit.com/1ByLjOV/tF4zfqKLFC",
			"visitedCount":"76402",
			"timeAdded":"1350132994",
			"timeDisplay":"2012-10-13 14:56:34"
		},
		{
			"domain":"Vub",
			"selection":"v6SyvPqQSH1",
			"url":"http://www.Vub.com/bZSzDJS/zJ0l17ZQ08",
			"visitedCount":"200887",
			"timeAdded":"1368053845",
			"timeDisplay":"2013-05-09 00:57:25"
		},
		{
			"domain":"Reddit",
			"selection":"6MWY2EmSSVW",
			"url":"http://www.Reddit.com/51Eyvbm/tuNvLYMeXI",
			"visitedCount":"359645",
			"timeAdded":"1363408237",
			"timeDisplay":"2013-03-16 05:30:37"
		},
		{
			"domain":"Vub",
			"selection":"W9ucJfzXsCG",
			"url":"http://www.Vub.com/MaYPu5n/9JdzMyVRvU",
			"visitedCount":"735722",
			"timeAdded":"1361611591",
			"timeDisplay":"2013-02-23 10:26:31"
		},
		{
			"domain":"Wikipedia",
			"selection":"4RYtuFTk5zL",
			"url":"http://www.Wikipedia.com/umdjbWh/ckAxQdsSFC",
			"visitedCount":"367309",
			"timeAdded":"1353547692",
			"timeDisplay":"2012-11-22 02:28:12"
		},
		{
			"domain":"Youtube",
			"selection":"czLBjRg3Qbo",
			"url":"http://www.Youtube.com/T9K1ped/DikjhCFMJC",
			"visitedCount":"183199",
			"timeAdded":"1365871802",
			"timeDisplay":"2013-04-13 18:50:02"
		},
		{
			"domain":"Vub",
			"selection":"1qQDijtOe4c",
			"url":"http://www.Vub.com/kbgqKDV/XuDaiL71qQ",
			"visitedCount":"52794",
			"timeAdded":"1351545962",
			"timeDisplay":"2012-10-29 22:26:02"
		},
		{
			"domain":"Vub",
			"selection":"A41W6wsrWe0",
			"url":"http://www.Vub.com/NqNtk9p/uXaLdjRWr9",
			"visitedCount":"813328",
			"timeAdded":"1345213397",
			"timeDisplay":"2012-08-17 16:23:17"
		},
		{
			"domain":"Vub",
			"selection":"p4B3LlMHTlp",
			"url":"http://www.Vub.com/2LWgNZe/lqZKO3coul",
			"visitedCount":"239793",
			"timeAdded":"1338285807",
			"timeDisplay":"2012-05-29 12:03:27"
		},
		{
			"domain":"Twitter",
			"selection":"wCL78MCvdis",
			"url":"http://www.Twitter.com/gtQly5x/la6ImynTdR",
			"visitedCount":"155691",
			"timeAdded":"1359475216",
			"timeDisplay":"2013-01-29 17:00:16"
		},
		{
			"domain":"Reddit",
			"selection":"jL8lERww5Na",
			"url":"http://www.Reddit.com/RkkMc19/KZVaYRlv42",
			"visitedCount":"208080",
			"timeAdded":"1340893203",
			"timeDisplay":"2012-06-28 16:20:03"
		},
		{
			"domain":"Reddit",
			"selection":"YL4YY12ngLY",
			"url":"http://www.Reddit.com/Kwme8y3/7Z7ZZuwqSD",
			"visitedCount":"467334",
			"timeAdded":"1363550393",
			"timeDisplay":"2013-03-17 20:59:53"
		},
		{
			"domain":"Facebook",
			"selection":"CHUjOJSljh4",
			"url":"http://www.Facebook.com/U2MqTLT/420O812lUy",
			"visitedCount":"584198",
			"timeAdded":"1359027620",
			"timeDisplay":"2013-01-24 12:40:20"
		},
		{
			"domain":"Facebook",
			"selection":"lyDLWp5cddx",
			"url":"http://www.Facebook.com/l0v7zwd/qd5uxA9lDZ",
			"visitedCount":"317409",
			"timeAdded":"1353770909",
			"timeDisplay":"2012-11-24 16:28:29"
		},
		{
			"domain":"Reddit",
			"selection":"s34n36xq76g",
			"url":"http://www.Reddit.com/MevpSUY/dXuY0jKhtB",
			"visitedCount":"367397",
			"timeAdded":"1344030070",
			"timeDisplay":"2012-08-03 23:41:10"
		},
		{
			"domain":"Amazon",
			"selection":"0gdtWeIfTp1",
			"url":"http://www.Amazon.com/XTEV560/NEYgwCHixB",
			"visitedCount":"274633",
			"timeAdded":"1339795891",
			"timeDisplay":"2012-06-15 23:31:31"
		},
		{
			"domain":"Wikipedia",
			"selection":"eEF81Fh9ZUI",
			"url":"http://www.Wikipedia.com/dmMUzMY/llt5Cmg3ud",
			"visitedCount":"173145",
			"timeAdded":"1355181685",
			"timeDisplay":"2012-12-11 00:21:25"
		},
		{
			"domain":"Youtube",
			"selection":"WZMjhbTgOqE",
			"url":"http://www.Youtube.com/LY1ZXiE/i5kbFnTGA1",
			"visitedCount":"488421",
			"timeAdded":"1345987967",
			"timeDisplay":"2012-08-26 15:32:47"
		},
		{
			"domain":"Google",
			"selection":"rzHpyi0cqlV",
			"url":"http://www.Google.com/W6E0fIH/olkza5K1kf",
			"visitedCount":"477077",
			"timeAdded":"1344984396",
			"timeDisplay":"2012-08-15 00:46:36"
		},
		{
			"domain":"Google",
			"selection":"eWp1NL1Ygob",
			"url":"http://www.Google.com/1HTtegA/074rH5uG5c",
			"visitedCount":"10221",
			"timeAdded":"1346705329",
			"timeDisplay":"2012-09-03 22:48:49"
		},
		{
			"domain":"Twitter",
			"selection":"nOcszMkis4P",
			"url":"http://www.Twitter.com/ORHQfYy/zbTQfJ1crr",
			"visitedCount":"740721",
			"timeAdded":"1362293400",
			"timeDisplay":"2013-03-03 07:50:00"
		},
		{
			"domain":"Google",
			"selection":"JPRX4fbv5o1",
			"url":"http://www.Google.com/eSXUveI/EnqgypUjsU",
			"visitedCount":"961993",
			"timeAdded":"1346762278",
			"timeDisplay":"2012-09-04 14:37:58"
		},
		{
			"domain":"Google",
			"selection":"TAcPPR5kg2v",
			"url":"http://www.Google.com/NknYYia/oCMm5VWcfq",
			"visitedCount":"142295",
			"timeAdded":"1354181394",
			"timeDisplay":"2012-11-29 10:29:54"
		},
		{
			"domain":"Facebook",
			"selection":"QjwPMed0qe8",
			"url":"http://www.Facebook.com/5lk0IYZ/s9L9vu4lKR",
			"visitedCount":"128512",
			"timeAdded":"1362775585",
			"timeDisplay":"2013-03-08 21:46:25"
		},
		{
			"domain":"Wikipedia",
			"selection":"5ANyb0KxETA",
			"url":"http://www.Wikipedia.com/3AAzrie/jarwX6CsC8",
			"visitedCount":"584085",
			"timeAdded":"1350238869",
			"timeDisplay":"2012-10-14 20:21:09"
		},
		{
			"domain":"Wikipedia",
			"selection":"VEaCepfKskB",
			"url":"http://www.Wikipedia.com/QvSbvIM/jweWG5zf0O",
			"visitedCount":"600445",
			"timeAdded":"1367943078",
			"timeDisplay":"2013-05-07 18:11:18"
		},
		{
			"domain":"Reddit",
			"selection":"pNYR2rUaL35",
			"url":"http://www.Reddit.com/N2vjZrH/kA9BnID30n",
			"visitedCount":"24325",
			"timeAdded":"1341868491",
			"timeDisplay":"2012-07-09 23:14:51"
		},
		{
			"domain":"Google",
			"selection":"NAQXSY3Opua",
			"url":"http://www.Google.com/FCug4g1/oM1ZLbXCjb",
			"visitedCount":"725136",
			"timeAdded":"1350410652",
			"timeDisplay":"2012-10-16 20:04:12"
		},
		{
			"domain":"Reddit",
			"selection":"vtA0QvNrnJX",
			"url":"http://www.Reddit.com/KhjEHlX/iHWKTCfXPU",
			"visitedCount":"919892",
			"timeAdded":"1355855014",
			"timeDisplay":"2012-12-18 19:23:34"
		},
		{
			"domain":"Wikipedia",
			"selection":"VMO4k7fk0Ak",
			"url":"http://www.Wikipedia.com/07NbXnA/7tTq7GXxF1",
			"visitedCount":"787021",
			"timeAdded":"1343972225",
			"timeDisplay":"2012-08-03 07:37:05"
		},
		{
			"domain":"Amazon",
			"selection":"FMVI55ftCdE",
			"url":"http://www.Amazon.com/oNLDAow/ZDnO1c2CGD",
			"visitedCount":"389955",
			"timeAdded":"1354849911",
			"timeDisplay":"2012-12-07 04:11:51"
		},
		{
			"domain":"Vub",
			"selection":"6reVFEGphCh",
			"url":"http://www.Vub.com/HRB3BVv/iHuDfNsXP9",
			"visitedCount":"738047",
			"timeAdded":"1351007123",
			"timeDisplay":"2012-10-23 17:45:23"
		},
		{
			"domain":"Google",
			"selection":"ArDqSEFqeqJ",
			"url":"http://www.Google.com/BU5y57T/f8FbMvOvBe",
			"visitedCount":"279004",
			"timeAdded":"1353895304",
			"timeDisplay":"2012-11-26 03:01:44"
		},
		{
			"domain":"Wikipedia",
			"selection":"fkMbr0aR2aV",
			"url":"http://www.Wikipedia.com/26j2avs/04SkNAUFkX",
			"visitedCount":"415194",
			"timeAdded":"1367370979",
			"timeDisplay":"2013-05-01 03:16:19"
		},
		{
			"domain":"Reddit",
			"selection":"Z7q5zZZYlgt",
			"url":"http://www.Reddit.com/rdYU8Tf/RPkhu3j49W",
			"visitedCount":"852236",
			"timeAdded":"1365712030",
			"timeDisplay":"2013-04-11 22:27:10"
		},
		{
			"domain":"Youtube",
			"selection":"KeTODjgqIvA",
			"url":"http://www.Youtube.com/uqPnHRz/SKkkjOp63w",
			"visitedCount":"708210",
			"timeAdded":"1343707868",
			"timeDisplay":"2012-07-31 06:11:08"
		},
		{
			"domain":"Reddit",
			"selection":"kxhq8kOkRNJ",
			"url":"http://www.Reddit.com/VXEtevp/nWerRseWIW",
			"visitedCount":"19750",
			"timeAdded":"1357848517",
			"timeDisplay":"2013-01-10 21:08:37"
		},
		{
			"domain":"Facebook",
			"selection":"A0Vk3uCTuTn",
			"url":"http://www.Facebook.com/Gl3oDjs/0E7Phrs0qH",
			"visitedCount":"435873",
			"timeAdded":"1356276922",
			"timeDisplay":"2012-12-23 16:35:22"
		},
		{
			"domain":"Reddit",
			"selection":"B9BHi7xFPhN",
			"url":"http://www.Reddit.com/DEHnKxs/5pxTHPFfe3",
			"visitedCount":"457559",
			"timeAdded":"1367549776",
			"timeDisplay":"2013-05-03 04:56:16"
		},
		{
			"domain":"Amazon",
			"selection":"KdDjATnmRiV",
			"url":"http://www.Amazon.com/AKy8xeC/zHQwpudGWZ",
			"visitedCount":"403870",
			"timeAdded":"1368556572",
			"timeDisplay":"2013-05-14 20:36:12"
		},
		{
			"domain":"Facebook",
			"selection":"7a0AZcIuzlr",
			"url":"http://www.Facebook.com/o0L1LNP/CT88NOyt74",
			"visitedCount":"791007",
			"timeAdded":"1343109627",
			"timeDisplay":"2012-07-24 08:00:27"
		},
		{
			"domain":"Wikipedia",
			"selection":"FUWtovjo6Rp",
			"url":"http://www.Wikipedia.com/nesPx0h/qAQWfY3T8B",
			"visitedCount":"401364",
			"timeAdded":"1340156265",
			"timeDisplay":"2012-06-20 03:37:45"
		},
		{
			"domain":"Vub",
			"selection":"h9hqyvYVlwn",
			"url":"http://www.Vub.com/bivCwoJ/xGMByJv3dV",
			"visitedCount":"565225",
			"timeAdded":"1359186619",
			"timeDisplay":"2013-01-26 08:50:19"
		},
		{
			"domain":"Vub",
			"selection":"a126kiJr3T5",
			"url":"http://www.Vub.com/Ombyk3J/wUKkrvJne6",
			"visitedCount":"700551",
			"timeAdded":"1347187359",
			"timeDisplay":"2012-09-09 12:42:39"
		},
		{
			"domain":"Reddit",
			"selection":"D89JQJeA5PV",
			"url":"http://www.Reddit.com/ydPwNwp/IuPYZD0yKx",
			"visitedCount":"154460",
			"timeAdded":"1361373459",
			"timeDisplay":"2013-02-20 16:17:39"
		},
		{
			"domain":"Facebook",
			"selection":"BgOXPRPbFLV",
			"url":"http://www.Facebook.com/cvFgM47/WhZwtxFDP6",
			"visitedCount":"164038",
			"timeAdded":"1353808706",
			"timeDisplay":"2012-11-25 02:58:26"
		},
		{
			"domain":"Amazon",
			"selection":"fODkBQ0Xb9j",
			"url":"http://www.Amazon.com/aAWVVuW/BmsdoFPEIM",
			"visitedCount":"540286",
			"timeAdded":"1365260699",
			"timeDisplay":"2013-04-06 17:04:59"
		},
		{
			"domain":"Vub",
			"selection":"6LIlLU8ZxEw",
			"url":"http://www.Vub.com/MfvwbDf/zEZvBfBvDx",
			"visitedCount":"894688",
			"timeAdded":"1343864595",
			"timeDisplay":"2012-08-02 01:43:15"
		},
		{
			"domain":"Google",
			"selection":"YpghVwe6Xlc",
			"url":"http://www.Google.com/G8J4bVX/4o1sslq3Yo",
			"visitedCount":"219532",
			"timeAdded":"1366896879",
			"timeDisplay":"2013-04-25 15:34:39"
		},
		{
			"domain":"Reddit",
			"selection":"dyk66s4nvva",
			"url":"http://www.Reddit.com/CJv4QYe/fe8iJOEma5",
			"visitedCount":"221418",
			"timeAdded":"1342801083",
			"timeDisplay":"2012-07-20 18:18:03"
		},
		{
			"domain":"Google",
			"selection":"VlJFQfOt3xI",
			"url":"http://www.Google.com/lyTzbhN/IPGlQ7LZpG",
			"visitedCount":"32019",
			"timeAdded":"1344935778",
			"timeDisplay":"2012-08-14 11:16:18"
		},
		{
			"domain":"Youtube",
			"selection":"wJRs0FMJf75",
			"url":"http://www.Youtube.com/v0sDqDE/eNqBdJ2mEk",
			"visitedCount":"287729",
			"timeAdded":"1350155993",
			"timeDisplay":"2012-10-13 21:19:53"
		},
		{
			"domain":"Google",
			"selection":"654oU94cRTe",
			"url":"http://www.Google.com/VtGfY7v/6pQaTu5INQ",
			"visitedCount":"844319",
			"timeAdded":"1352470635",
			"timeDisplay":"2012-11-09 15:17:15"
		},
		{
			"domain":"Twitter",
			"selection":"FdmC2FcIWB4",
			"url":"http://www.Twitter.com/dNPkk4d/ThSFnJMwL2",
			"visitedCount":"386892",
			"timeAdded":"1357476704",
			"timeDisplay":"2013-01-06 13:51:44"
		},
		{
			"domain":"Reddit",
			"selection":"I2irTug9Tzc",
			"url":"http://www.Reddit.com/RgGcEBI/ERRPwFVFmo",
			"visitedCount":"311235",
			"timeAdded":"1350780875",
			"timeDisplay":"2012-10-21 02:54:35"
		},
		{
			"domain":"Amazon",
			"selection":"MPq4zv4cAye",
			"url":"http://www.Amazon.com/RomBkVU/mTW3JXfuVM",
			"visitedCount":"14904",
			"timeAdded":"1355789897",
			"timeDisplay":"2012-12-18 01:18:17"
		},
		{
			"domain":"Twitter",
			"selection":"kCaYl9zsB96",
			"url":"http://www.Twitter.com/vvAPodM/D67NmvAjV4",
			"visitedCount":"18920",
			"timeAdded":"1351724097",
			"timeDisplay":"2012-10-31 23:54:57"
		},
		{
			"domain":"Wikipedia",
			"selection":"gFeGo3iixHj",
			"url":"http://www.Wikipedia.com/chWVvY5/7KMWik4Vbc",
			"visitedCount":"15296",
			"timeAdded":"1362645855",
			"timeDisplay":"2013-03-07 09:44:15"
		},
		{
			"domain":"Facebook",
			"selection":"OkfOomHsXDH",
			"url":"http://www.Facebook.com/0rMWppf/Aa9qHvGl7i",
			"visitedCount":"587855",
			"timeAdded":"1354137483",
			"timeDisplay":"2012-11-28 22:18:03"
		},
		{
			"domain":"Youtube",
			"selection":"JNUe5lhh2Py",
			"url":"http://www.Youtube.com/ikrJ4iP/4EwBR8ToQ6",
			"visitedCount":"418541",
			"timeAdded":"1366862315",
			"timeDisplay":"2013-04-25 05:58:35"
		},
		{
			"domain":"Youtube",
			"selection":"ExwxBBsPYOg",
			"url":"http://www.Youtube.com/5qAhv16/vSXljjZogm",
			"visitedCount":"391116",
			"timeAdded":"1358007550",
			"timeDisplay":"2013-01-12 17:19:10"
		},
		{
			"domain":"Facebook",
			"selection":"4LY1Wo8pQBj",
			"url":"http://www.Facebook.com/1GFmDLk/VBLxbtoAbG",
			"visitedCount":"333965",
			"timeAdded":"1361068559",
			"timeDisplay":"2013-02-17 03:35:59"
		},
		{
			"domain":"Youtube",
			"selection":"z2VYN0BoW3k",
			"url":"http://www.Youtube.com/8KACQci/HOs98mQ6Fr",
			"visitedCount":"549696",
			"timeAdded":"1360848104",
			"timeDisplay":"2013-02-14 14:21:44"
		},
		{
			"domain":"Reddit",
			"selection":"G0OrQ2sghvU",
			"url":"http://www.Reddit.com/6aQxWK8/Atgl3AFqQh",
			"visitedCount":"748191",
			"timeAdded":"1350558569",
			"timeDisplay":"2012-10-18 13:09:29"
		},
		{
			"domain":"Google",
			"selection":"H4XQnPGgjNP",
			"url":"http://www.Google.com/jxvtdz6/CIpe1GBqGF",
			"visitedCount":"45033",
			"timeAdded":"1368787122",
			"timeDisplay":"2013-05-17 12:38:42"
		},
		{
			"domain":"Wikipedia",
			"selection":"t7KyG40eoXe",
			"url":"http://www.Wikipedia.com/YR3ZgrA/xZwfaWgwif",
			"visitedCount":"268411",
			"timeAdded":"1367736276",
			"timeDisplay":"2013-05-05 08:44:36"
		},
		{
			"domain":"Vub",
			"selection":"2nvnrS4aYrM",
			"url":"http://www.Vub.com/9TRHFX6/4HsFRyTKIk",
			"visitedCount":"472665",
			"timeAdded":"1362744465",
			"timeDisplay":"2013-03-08 13:07:45"
		},
		{
			"domain":"Reddit",
			"selection":"JCZV45qRyUj",
			"url":"http://www.Reddit.com/4DU14vw/uEhcrdvIpx",
			"visitedCount":"883914",
			"timeAdded":"1346313666",
			"timeDisplay":"2012-08-30 10:01:06"
		},
		{
			"domain":"Wikipedia",
			"selection":"HxSXNwgIa9w",
			"url":"http://www.Wikipedia.com/h3jPrDK/irSK2ce3SP",
			"visitedCount":"788826",
			"timeAdded":"1354299403",
			"timeDisplay":"2012-11-30 19:16:43"
		},
		{
			"domain":"Amazon",
			"selection":"i2Fu5x0OB9M",
			"url":"http://www.Amazon.com/WFTdlQP/Dtj5qXDHgw",
			"visitedCount":"418261",
			"timeAdded":"1347220574",
			"timeDisplay":"2012-09-09 21:56:14"
		},
		{
			"domain":"Google",
			"selection":"yCoOw8xjxz5",
			"url":"http://www.Google.com/VWeCmaX/hYTlDw8h7w",
			"visitedCount":"115886",
			"timeAdded":"1365711401",
			"timeDisplay":"2013-04-11 22:16:41"
		},
		{
			"domain":"Facebook",
			"selection":"WiVPA685Rdo",
			"url":"http://www.Facebook.com/czG4ZxK/GdL0FDZA7d",
			"visitedCount":"8713",
			"timeAdded":"1369218328",
			"timeDisplay":"2013-05-22 12:25:28"
		},
		{
			"domain":"Amazon",
			"selection":"bYF8777Ot0B",
			"url":"http://www.Amazon.com/TbpC7c3/NvZBPjAFSf",
			"visitedCount":"680419",
			"timeAdded":"1363754748",
			"timeDisplay":"2013-03-20 05:45:48"
		},
		{
			"domain":"Facebook",
			"selection":"msceYofuCiK",
			"url":"http://www.Facebook.com/VHdKJ0H/Mz4KuAbMwG",
			"visitedCount":"90024",
			"timeAdded":"1361375547",
			"timeDisplay":"2013-02-20 16:52:27"
		},
		{
			"domain":"Twitter",
			"selection":"JuaF6Wpa9wn",
			"url":"http://www.Twitter.com/Fbup1mB/Ft7txcm4wC",
			"visitedCount":"80788",
			"timeAdded":"1366132211",
			"timeDisplay":"2013-04-16 19:10:11"
		},
		{
			"domain":"Facebook",
			"selection":"zsipoKvbAYX",
			"url":"http://www.Facebook.com/Ej7LrBc/yvjBGrXi9s",
			"visitedCount":"114406",
			"timeAdded":"1352031257",
			"timeDisplay":"2012-11-04 13:14:17"
		},
		{
			"domain":"Vub",
			"selection":"ttMVFA2MfFy",
			"url":"http://www.Vub.com/na4yt2x/8dsDUaBxUK",
			"visitedCount":"513147",
			"timeAdded":"1344384164",
			"timeDisplay":"2012-08-08 02:02:44"
		},
		{
			"domain":"Google",
			"selection":"ua8TZL8SIJV",
			"url":"http://www.Google.com/wwzY1oe/urdvlrkewG",
			"visitedCount":"141053",
			"timeAdded":"1361421897",
			"timeDisplay":"2013-02-21 05:44:57"
		},
		{
			"domain":"Google",
			"selection":"AyVZQwwrsCx",
			"url":"http://www.Google.com/FEIvMX8/ahAi96SIJK",
			"visitedCount":"220951",
			"timeAdded":"1363410995",
			"timeDisplay":"2013-03-16 06:16:35"
		},
		{
			"domain":"Youtube",
			"selection":"w8kBIaMwTlU",
			"url":"http://www.Youtube.com/8ZdXfBm/le8mER2SCT",
			"visitedCount":"322799",
			"timeAdded":"1351260797",
			"timeDisplay":"2012-10-26 16:13:17"
		},
		{
			"domain":"Amazon",
			"selection":"ESwaXHsSgHZ",
			"url":"http://www.Amazon.com/fnFkSjJ/wXhvMihBDe",
			"visitedCount":"394180",
			"timeAdded":"1366294270",
			"timeDisplay":"2013-04-18 16:11:10"
		},
		{
			"domain":"Reddit",
			"selection":"M6fArOHOGXA",
			"url":"http://www.Reddit.com/fmb7kWh/cXg6BGxLpg",
			"visitedCount":"797440",
			"timeAdded":"1353785737",
			"timeDisplay":"2012-11-24 20:35:37"
		},
		{
			"domain":"Wikipedia",
			"selection":"FJ7MvEUX53R",
			"url":"http://www.Wikipedia.com/j9BLmO9/0jmknBu3NJ",
			"visitedCount":"530010",
			"timeAdded":"1341453808",
			"timeDisplay":"2012-07-05 04:03:28"
		},
		{
			"domain":"Wikipedia",
			"selection":"sTtg4aWHKk1",
			"url":"http://www.Wikipedia.com/IrUUgcQ/aAHJkHtW6X",
			"visitedCount":"167343",
			"timeAdded":"1365490921",
			"timeDisplay":"2013-04-09 09:02:01"
		},
		{
			"domain":"Reddit",
			"selection":"ghfOEescw0o",
			"url":"http://www.Reddit.com/cy9TgNR/xIH7fP3mzk",
			"visitedCount":"939162",
			"timeAdded":"1339241862",
			"timeDisplay":"2012-06-09 13:37:42"
		},
		{
			"domain":"Facebook",
			"selection":"w1QWURUrJbM",
			"url":"http://www.Facebook.com/F9sW3bv/zoaU47AMbW",
			"visitedCount":"971804",
			"timeAdded":"1368291535",
			"timeDisplay":"2013-05-11 18:58:55"
		},
		{
			"domain":"Youtube",
			"selection":"AQHHuHSTI7v",
			"url":"http://www.Youtube.com/YuoK7qa/1h5ZpTMjuJ",
			"visitedCount":"85178",
			"timeAdded":"1358931563",
			"timeDisplay":"2013-01-23 09:59:23"
		},
		{
			"domain":"Twitter",
			"selection":"o58nyXuWAcS",
			"url":"http://www.Twitter.com/0BI0HP5/3zt6gnWSaq",
			"visitedCount":"336208",
			"timeAdded":"1343590251",
			"timeDisplay":"2012-07-29 21:30:51"
		},
		{
			"domain":"Reddit",
			"selection":"Q7BXcoYboXi",
			"url":"http://www.Reddit.com/u4OfvFy/1vUZpU4Bcf",
			"visitedCount":"122280",
			"timeAdded":"1366361331",
			"timeDisplay":"2013-04-19 10:48:51"
		},
		{
			"domain":"Vub",
			"selection":"1Gkqr74he0t",
			"url":"http://www.Vub.com/1Eo6e4r/wyPz7SPI9m",
			"visitedCount":"135986",
			"timeAdded":"1369610468",
			"timeDisplay":"2013-05-27 01:21:08"
		},
		{
			"domain":"Twitter",
			"selection":"xD2WcuQRlv6",
			"url":"http://www.Twitter.com/Nh5azk8/PYMrDwRERm",
			"visitedCount":"216760",
			"timeAdded":"1345073364",
			"timeDisplay":"2012-08-16 01:29:24"
		},
		{
			"domain":"Wikipedia",
			"selection":"YtvoBX2jvTg",
			"url":"http://www.Wikipedia.com/815BqrS/rCkcHrJOvn",
			"visitedCount":"812518",
			"timeAdded":"1342575875",
			"timeDisplay":"2012-07-18 03:44:35"
		}
	],
	"links": [
		{
			"source":"ExwxBBsPYOg",
			"target":"YPXb9L1la2E"
		},
		{
			"source":"EGu7xZjvo63",
			"target":"h9hqyvYVlwn"
		},
		{
			"source":"w1QWURUrJbM",
			"target":"xD2WcuQRlv6"
		},
		{
			"source":"w1QWURUrJbM",
			"target":"YPXb9L1la2E"
		},
		{
			"source":"I2irTug9Tzc",
			"target":"654oU94cRTe"
		},
		{
			"source":"p4B3LlMHTlp",
			"target":"lyDLWp5cddx"
		},
		{
			"source":"4RYtuFTk5zL",
			"target":"fDr6tPSy0p4"
		},
		{
			"source":"OkfOomHsXDH",
			"target":"YtvoBX2jvTg"
		},
		{
			"source":"I2irTug9Tzc",
			"target":"6reVFEGphCh"
		},
		{
			"source":"wCL78MCvdis",
			"target":"wCL78MCvdis"
		},
		{
			"source":"A0Vk3uCTuTn",
			"target":"5ANyb0KxETA"
		},
		{
			"source":"ExwxBBsPYOg",
			"target":"G0OrQ2sghvU"
		},
		{
			"source":"VlJFQfOt3xI",
			"target":"FdmC2FcIWB4"
		},
		{
			"source":"D89JQJeA5PV",
			"target":"VMO4k7fk0Ak"
		},
		{
			"source":"KeTODjgqIvA",
			"target":"MPq4zv4cAye"
		},
		{
			"source":"CHUjOJSljh4",
			"target":"0QnZlHowE1J"
		},
		{
			"source":"WZMjhbTgOqE",
			"target":"kCaYl9zsB96"
		},
		{
			"source":"wCL78MCvdis",
			"target":"ExwxBBsPYOg"
		},
		{
			"source":"kCaYl9zsB96",
			"target":"1Gkqr74he0t"
		},
		{
			"source":"w1QWURUrJbM",
			"target":"6MWY2EmSSVW"
		},
		{
			"source":"D89JQJeA5PV",
			"target":"EGu7xZjvo63"
		},
		{
			"source":"nOcszMkis4P",
			"target":"YtvoBX2jvTg"
		},
		{
			"source":"zsipoKvbAYX",
			"target":"jL8lERww5Na"
		},
		{
			"source":"AyVZQwwrsCx",
			"target":"kxhq8kOkRNJ"
		},
		{
			"source":"7a0AZcIuzlr",
			"target":"YpghVwe6Xlc"
		},
		{
			"source":"6gi7G7MqRa3",
			"target":"w8kBIaMwTlU"
		},
		{
			"source":"wCL78MCvdis",
			"target":"wJRs0FMJf75"
		},
		{
			"source":"JNUe5lhh2Py",
			"target":"A41W6wsrWe0"
		},
		{
			"source":"AQHHuHSTI7v",
			"target":"0gdtWeIfTp1"
		},
		{
			"source":"msceYofuCiK",
			"target":"A0Vk3uCTuTn"
		},
		{
			"source":"M6fArOHOGXA",
			"target":"xt8GP79XEDq"
		},
		{
			"source":"JCZV45qRyUj",
			"target":"fkMbr0aR2aV"
		},
		{
			"source":"M6fArOHOGXA",
			"target":"KdDjATnmRiV"
		},
		{
			"source":"kxhq8kOkRNJ",
			"target":"B9BHi7xFPhN"
		},
		{
			"source":"o58nyXuWAcS",
			"target":"BgOXPRPbFLV"
		},
		{
			"source":"EGu7xZjvo63",
			"target":"QjwPMed0qe8"
		},
		{
			"source":"kxhq8kOkRNJ",
			"target":"lyDLWp5cddx"
		},
		{
			"source":"pNYR2rUaL35",
			"target":"t7KyG40eoXe"
		},
		{
			"source":"654oU94cRTe",
			"target":"vtA0QvNrnJX"
		},
		{
			"source":"VlJFQfOt3xI",
			"target":"HxSXNwgIa9w"
		},
		{
			"source":"Z7q5zZZYlgt",
			"target":"WZMjhbTgOqE"
		},
		{
			"source":"6reVFEGphCh",
			"target":"1Gkqr74he0t"
		},
		{
			"source":"h9hqyvYVlwn",
			"target":"VlJFQfOt3xI"
		},
		{
			"source":"7a0AZcIuzlr",
			"target":"FdmC2FcIWB4"
		},
		{
			"source":"h9hqyvYVlwn",
			"target":"EGu7xZjvo63"
		},
		{
			"source":"kCaYl9zsB96",
			"target":"o58nyXuWAcS"
		},
		{
			"source":"t7KyG40eoXe",
			"target":"ttMVFA2MfFy"
		},
		{
			"source":"HxSXNwgIa9w",
			"target":"654oU94cRTe"
		},
		{
			"source":"z2VYN0BoW3k",
			"target":"VMO4k7fk0Ak"
		},
		{
			"source":"A0Vk3uCTuTn",
			"target":"M6fArOHOGXA"
		},
		{
			"source":"HxSXNwgIa9w",
			"target":"H4XQnPGgjNP"
		},
		{
			"source":"6MWY2EmSSVW",
			"target":"A0Vk3uCTuTn"
		},
		{
			"source":"ArDqSEFqeqJ",
			"target":"yCoOw8xjxz5"
		},
		{
			"source":"KdDjATnmRiV",
			"target":"YPXb9L1la2E"
		},
		{
			"source":"6reVFEGphCh",
			"target":"654oU94cRTe"
		},
		{
			"source":"TAcPPR5kg2v",
			"target":"KdDjATnmRiV"
		},
		{
			"source":"ExwxBBsPYOg",
			"target":"D89JQJeA5PV"
		},
		{
			"source":"NAQXSY3Opua",
			"target":"gFeGo3iixHj"
		},
		{
			"source":"GjiFc5TwZRn",
			"target":"xt8GP79XEDq"
		},
		{
			"source":"1Gkqr74he0t",
			"target":"bYF8777Ot0B"
		},
		{
			"source":"o58nyXuWAcS",
			"target":"zsipoKvbAYX"
		},
		{
			"source":"jL8lERww5Na",
			"target":"6LIlLU8ZxEw"
		},
		{
			"source":"A0Vk3uCTuTn",
			"target":"AyVZQwwrsCx"
		},
		{
			"source":"lyDLWp5cddx",
			"target":"654oU94cRTe"
		},
		{
			"source":"FJ7MvEUX53R",
			"target":"654oU94cRTe"
		},
		{
			"source":"VMO4k7fk0Ak",
			"target":"MPq4zv4cAye"
		},
		{
			"source":"fkMbr0aR2aV",
			"target":"YtvoBX2jvTg"
		},
		{
			"source":"i2Fu5x0OB9M",
			"target":"VMO4k7fk0Ak"
		},
		{
			"source":"4RYtuFTk5zL",
			"target":"ESwaXHsSgHZ"
		},
		{
			"source":"654oU94cRTe",
			"target":"FUWtovjo6Rp"
		},
		{
			"source":"fkMbr0aR2aV",
			"target":"ghfOEescw0o"
		},
		{
			"source":"I2irTug9Tzc",
			"target":"YtvoBX2jvTg"
		},
		{
			"source":"KeTODjgqIvA",
			"target":"wCL78MCvdis"
		},
		{
			"source":"gFeGo3iixHj",
			"target":"HxSXNwgIa9w"
		},
		{
			"source":"A41W6wsrWe0",
			"target":"BgOXPRPbFLV"
		},
		{
			"source":"w8kBIaMwTlU",
			"target":"A41W6wsrWe0"
		},
		{
			"source":"s34n36xq76g",
			"target":"7a0AZcIuzlr"
		},
		{
			"source":"ua8TZL8SIJV",
			"target":"CHUjOJSljh4"
		},
		{
			"source":"QjwPMed0qe8",
			"target":"dyk66s4nvva"
		},
		{
			"source":"ESwaXHsSgHZ",
			"target":"ttMVFA2MfFy"
		},
		{
			"source":"JuaF6Wpa9wn",
			"target":"I2irTug9Tzc"
		},
		{
			"source":"BgOXPRPbFLV",
			"target":"sTtg4aWHKk1"
		},
		{
			"source":"jL8lERww5Na",
			"target":"KeTODjgqIvA"
		},
		{
			"source":"xt8GP79XEDq",
			"target":"VMO4k7fk0Ak"
		},
		{
			"source":"0QnZlHowE1J",
			"target":"6MWY2EmSSVW"
		},
		{
			"source":"HxSXNwgIa9w",
			"target":"7a0AZcIuzlr"
		},
		{
			"source":"a126kiJr3T5",
			"target":"z2VYN0BoW3k"
		},
		{
			"source":"WiVPA685Rdo",
			"target":"NAQXSY3Opua"
		},
		{
			"source":"6gi7G7MqRa3",
			"target":"JNUe5lhh2Py"
		},
		{
			"source":"i2Fu5x0OB9M",
			"target":"6MWY2EmSSVW"
		},
		{
			"source":"Q7BXcoYboXi",
			"target":"1Gkqr74he0t"
		},
		{
			"source":"FUWtovjo6Rp",
			"target":"YtvoBX2jvTg"
		},
		{
			"source":"JuaF6Wpa9wn",
			"target":"nOcszMkis4P"
		},
		{
			"source":"s34n36xq76g",
			"target":"rzHpyi0cqlV"
		},
		{
			"source":"pNYR2rUaL35",
			"target":"rzHpyi0cqlV"
		},
		{
			"source":"o58nyXuWAcS",
			"target":"fODkBQ0Xb9j"
		},
		{
			"source":"lyDLWp5cddx",
			"target":"Z7q5zZZYlgt"
		},
		{
			"source":"FMVI55ftCdE",
			"target":"ExwxBBsPYOg"
		},
		{
			"source":"W9ucJfzXsCG",
			"target":"jL8lERww5Na"
		},
		{
			"source":"6LIlLU8ZxEw",
			"target":"2nvnrS4aYrM"
		},
		{
			"source":"AQHHuHSTI7v",
			"target":"AQHHuHSTI7v"
		},
		{
			"source":"6LIlLU8ZxEw",
			"target":"p4B3LlMHTlp"
		},
		{
			"source":"FdmC2FcIWB4",
			"target":"a126kiJr3T5"
		},
		{
			"source":"jL8lERww5Na",
			"target":"NHdpoq81Ot3"
		},
		{
			"source":"czLBjRg3Qbo",
			"target":"KdDjATnmRiV"
		},
		{
			"source":"YL4YY12ngLY",
			"target":"4RYtuFTk5zL"
		},
		{
			"source":"EGu7xZjvo63",
			"target":"D89JQJeA5PV"
		},
		{
			"source":"ghfOEescw0o",
			"target":"w1QWURUrJbM"
		},
		{
			"source":"zsipoKvbAYX",
			"target":"4RYtuFTk5zL"
		},
		{
			"source":"M6fArOHOGXA",
			"target":"KdDjATnmRiV"
		},
		{
			"source":"fDr6tPSy0p4",
			"target":"Q7BXcoYboXi"
		},
		{
			"source":"v6SyvPqQSH1",
			"target":"5ANyb0KxETA"
		},
		{
			"source":"B9BHi7xFPhN",
			"target":"w1QWURUrJbM"
		},
		{
			"source":"eEF81Fh9ZUI",
			"target":"MPq4zv4cAye"
		},
		{
			"source":"AyVZQwwrsCx",
			"target":"0gdtWeIfTp1"
		},
		{
			"source":"FUWtovjo6Rp",
			"target":"o58nyXuWAcS"
		},
		{
			"source":"t7KyG40eoXe",
			"target":"wJRs0FMJf75"
		},
		{
			"source":"h9hqyvYVlwn",
			"target":"JPRX4fbv5o1"
		},
		{
			"source":"6LIlLU8ZxEw",
			"target":"4LY1Wo8pQBj"
		},
		{
			"source":"eEF81Fh9ZUI",
			"target":"rzHpyi0cqlV"
		},
		{
			"source":"WiVPA685Rdo",
			"target":"nOcszMkis4P"
		},
		{
			"source":"ESwaXHsSgHZ",
			"target":"4LY1Wo8pQBj"
		},
		{
			"source":"v6SyvPqQSH1",
			"target":"Z7q5zZZYlgt"
		},
		{
			"source":"Z7q5zZZYlgt",
			"target":"M6fArOHOGXA"
		},
		{
			"source":"ua8TZL8SIJV",
			"target":"Z7q5zZZYlgt"
		},
		{
			"source":"wCL78MCvdis",
			"target":"A41W6wsrWe0"
		},
		{
			"source":"gFeGo3iixHj",
			"target":"YPXb9L1la2E"
		},
		{
			"source":"BgOXPRPbFLV",
			"target":"YpghVwe6Xlc"
		},
		{
			"source":"7a0AZcIuzlr",
			"target":"5ANyb0KxETA"
		},
		{
			"source":"Z7q5zZZYlgt",
			"target":"EGu7xZjvo63"
		},
		{
			"source":"kxhq8kOkRNJ",
			"target":"OkfOomHsXDH"
		},
		{
			"source":"czLBjRg3Qbo",
			"target":"A0Vk3uCTuTn"
		},
		{
			"source":"FJ7MvEUX53R",
			"target":"YpghVwe6Xlc"
		},
		{
			"source":"kxhq8kOkRNJ",
			"target":"5ANyb0KxETA"
		},
		{
			"source":"ExwxBBsPYOg",
			"target":"WiVPA685Rdo"
		},
		{
			"source":"dyk66s4nvva",
			"target":"JPRX4fbv5o1"
		},
		{
			"source":"kxhq8kOkRNJ",
			"target":"QjwPMed0qe8"
		},
		{
			"source":"eWp1NL1Ygob",
			"target":"eEF81Fh9ZUI"
		},
		{
			"source":"kCaYl9zsB96",
			"target":"ghfOEescw0o"
		},
		{
			"source":"JuaF6Wpa9wn",
			"target":"BgOXPRPbFLV"
		},
		{
			"source":"G0OrQ2sghvU",
			"target":"WZMjhbTgOqE"
		},
		{
			"source":"fODkBQ0Xb9j",
			"target":"AQHHuHSTI7v"
		},
		{
			"source":"I2irTug9Tzc",
			"target":"YPXb9L1la2E"
		},
		{
			"source":"w8kBIaMwTlU",
			"target":"FdmC2FcIWB4"
		},
		{
			"source":"0gdtWeIfTp1",
			"target":"CHUjOJSljh4"
		},
		{
			"source":"v6SyvPqQSH1",
			"target":"dyk66s4nvva"
		},
		{
			"source":"gFeGo3iixHj",
			"target":"JPRX4fbv5o1"
		},
		{
			"source":"pNYR2rUaL35",
			"target":"W9ucJfzXsCG"
		},
		{
			"source":"vtA0QvNrnJX",
			"target":"YPXb9L1la2E"
		},
		{
			"source":"M6fArOHOGXA",
			"target":"7a0AZcIuzlr"
		}
	]
}